LICENSE
MANIFEST.in
README.rst
setup.py
django_flatpages_i18n.egg-info/PKG-INFO
django_flatpages_i18n.egg-info/SOURCES.txt
django_flatpages_i18n.egg-info/dependency_links.txt
django_flatpages_i18n.egg-info/requires.txt
django_flatpages_i18n.egg-info/top_level.txt
flatpages_i18n/__init__.py
flatpages_i18n/admin.py
flatpages_i18n/middleware.py
flatpages_i18n/models.py
flatpages_i18n/urls.py
flatpages_i18n/views.py
flatpages_i18n/migrations/0001_initial.py
flatpages_i18n/migrations/0002_auto_20200619_1344.py
flatpages_i18n/migrations/0003_auto_20220714_1614.py
flatpages_i18n/migrations/0004_markdown_to_html.py
flatpages_i18n/migrations/0005_html_field.py
flatpages_i18n/migrations/__init__.py
flatpages_i18n/templates/.DS_Store
flatpages_i18n/templates/flatpages_i18n/default.html
flatpages_i18n/templates/flatpages_i18n/menu.html
flatpages_i18n/templatetags/__init__.py
flatpages_i18n/templatetags/flatpages_i18n.py