Metadata-Version: 2.1
Name: django-flatpages-i18n
Version: 2.0.2
Summary: Translatable flatpages
Home-page: https://github.com/PragmaticMates/django-flatpages-i18n
Author: Pragmatic Mates
Author-email: info@pragmaticmates.com
Maintainer: Pragmatic Mates
Maintainer-email: info@pragmaticmates.com
License: BSD License
Keywords: django flatpages translation i18n
Classifier: Programming Language :: Python
Classifier: Programming Language :: Python :: 3.7
Classifier: Operating System :: OS Independent
Classifier: Environment :: Web Environment
Classifier: Intended Audience :: Developers
Classifier: Framework :: Django
Classifier: License :: OSI Approved :: BSD License
License-File: LICENSE
Requires-Dist: django
Requires-Dist: django_modeltrans
Requires-Dist: django_mptt
Requires-Dist: markdown
Requires-Dist: martor
Requires-Dist: django-tinymce
Requires-Dist: django-pragmatic
